joywins_my_data_coupang_order/__init__.py
joywins_my_data_coupang_order/joywins_my_data_coupang_order.py
joywins_my_data_coupang_order-0.0.2.dist-info/LICENSE.txt
joywins_my_data_coupang_order-0.0.2.dist-info/METADATA
joywins_my_data_coupang_order-0.0.2.dist-info/WHEEL
joywins_my_data_coupang_order-0.0.2.dist-info/top_level.txt
joywins_my_data_coupang_order-0.0.2.dist-info/RECORD
