Metadata-Version: 2.1
Name: joywins_my_data_coupang_order
Version: 0.0.2
Summary: 쿠팡 주문 목록 스크래퍼
Home-page: https://github.com/JoyWins123/joywins_my_data_coupang_order
Author: joywins123
Author-email: joywins123 <joywins123@gmail.com>
Project-URL: Homepage, https://github.com/JoyWins123/joywins_my_data_coupang_order
Classifier: Development Status :: 3 - Alpha
Classifier: Intended Audience :: Developers
Classifier: Programming Language :: Python :: 3.8
Classifier: License :: OSI Approved :: MIT License
Classifier: Operating System :: OS Independent
Requires-Python: >=3.8
License-File: LICENSE.txt
